[{"name":"贝兰万德","enName":"Alireza Beiranvand","club":"拖拉机","position":"GK"},{"name":"侯赛尼","enName":"Hossein Hosseini","club":"塞帕罕","position":"GK"},{"name":"尼亚兹曼德","enName":"Payam Niazmand","club":"波斯波利斯","position":"GK"},{"name":"哈吉萨菲","enName":"Ehsan Hajsafi","club":"塞帕罕","position":"LB"},{"name":"穆罕马迪","enName":"Milad Mohammadi","club":"波斯波利斯","position":"LB"},{"name":"内马蒂","enName":"Ali Nemati","club":"福拉德","position":"CB"},{"name":"伊里","enName":"Danial Iri","club":"马拉万","position":"CB"},{"name":"哈利勒扎德","enName":"Shojae Khalilzadeh","club":"拖拉机","position":"CB"},{"name":"卡纳尼扎德甘","enName":"Kanaanizadegan","club":"波斯波利斯","position":"CB"},{"name":"尤塞菲","enName":"Arya Yousefi","club":"塞帕罕","position":"RB"},{"name":"哈尔达尼","enName":"Saleh Hardani","club":"埃斯特格拉尔","position":"RB"},{"name":"雷扎伊安","enName":"Ramin Rezaeian","club":"福拉德","position":"RB"},{"name":"贾汉巴赫什","enName":"Alireza Jahanbakhsh","club":"登德","position":"RW"},{"name":"埃扎托拉希","enName":"Saeid Ezatolahi","club":"沙巴艾哈利","position":"CDM"},{"name":"切什米","enName":"Rouzbeh Cheshmi","club":"埃斯特格拉尔","position":"CB"},{"name":"拉扎格尼亚","enName":"Amirmohammad Razaghnian","club":"埃斯特格拉尔","position":"CM"},{"name":"莫赫比","enName":"Mohammad Mohebi","club":"罗斯托夫","position":"LW"},{"name":"加耶迪","enName":"Mehdi Ghayedi","club":"纳斯尔","position":"RW"},{"name":"古多斯","enName":"Saman Ghoddos","club":"卡尔巴联合","position":"CAM"},{"name":"戈尔巴尼","enName":"Mohammad Ghorbani","club":"瓦赫达","position":"CDM"},{"name":"托拉比","enName":"Mehdi Torabi","club":"拖拉机","position":"RW"},{"name":"侯赛因扎德","enName":"Amirhossein Hosseinzadeh","club":"拖拉机","position":"LW"},{"name":"阿里普尔","enName":"Ali Alipour","club":"波斯波利斯","position":"ST"},{"name":"莫加努","enName":"Shahriar Moghanlou","club":"卡尔巴联合","position":"ST"},{"name":"达尔加希","enName":"Denis Dargahi","club":"标准列日","position":"ST"},{"name":"塔雷米","enName":"Mehdi Taremi","club":"奥林匹亚科斯","position":"ST"}]